dexa/__init__.py
dexa/__main__.py
dexa/cli/commands/config/__init__.py
dexa/cli/commands/config/extend.py
dexa/cli/commands/config/get.py
dexa/cli/commands/config/set.py
dexa/cli/commands/config/unset.py
dexa/cli/commands/root_command.py
dexa/cli/helpers/__init__.py
dexa/cli/helpers/converter.py
dexa/cli/helpers/printer.py
dexa/cli/styling/__init__.py
dexa/cli/styling/themes.py
dexa/config/__init__.py
dexa/config/constants.py
dexa/config/helpers.py
dexa/config/manager.py
dexa/config/mappings.py
dexa/logging/__init__.py
dexa/logging/formatters.py
dexa/logging/parsers.py
dexa/logging/text_tools.py
dexa/tui/components/.gitkeep
dexa/tui/css/.gitkeep
dexa/tui/css/demo.tcss
dexa/tui/css/noctis.tcss
dexa/tui/main_window.py
dexa/tui/themes.py
dexa-0.1.0a0.dist-info/METADATA
dexa-0.1.0a0.dist-info/WHEEL
dexa-0.1.0a0.dist-info/entry_points.txt
dexa-0.1.0a0.dist-info/licenses/LICENCE
dexa-0.1.0a0.dist-info/RECORD
