Metadata-Version: 2.4
Name: dexa
Version: 0.1.0a0
Summary: The ultimate terminal RPN calculator.
License: MIT
License-File: LICENCE
Author: Manoel Pereira de Queiroz
Author-email: mpq.dev@pm.me
Maintainer: Manoel Pereira de Queiroz
Maintainer-email: mpq.dev@pm.me
Requires-Python: >=3.11
Classifier: Development Status :: 1 - Planning
Classifier: Environment :: Console
Classifier: License :: OSI Approved :: MIT License
Classifier: Operating System :: OS Independent
Classifier: Programming Language :: Python :: 3
Classifier: Programming Language :: Python :: 3.11
Classifier: Programming Language :: Python :: 3.12
Classifier: Programming Language :: Python :: 3.13
Classifier: Programming Language :: Python :: 3.14
Classifier: Topic :: Software Development :: Libraries :: Python Modules
Classifier: Topic :: Terminals
Requires-Dist: art (>=6.5.0,<7.0.0)
Requires-Dist: click (>=8.1.0,<8.2.0)
Requires-Dist: nebulog (>=0.1.0,<0.2.0)
Requires-Dist: orbittings (>=0.2.0,<0.3.0)
Requires-Dist: platformdirs (>=4.5.0,<5.0.0)
Requires-Dist: rich (>=14.2.0,<15.0.0)
Requires-Dist: textual (>=6.5.0,<7.0.0)
Requires-Dist: typer[all] (>=0.20.0,<0.21.0)
Project-URL: Contributing Guidelines, https://gitlab.com/nummertopia/dexa/-/tree/master/CONTRIBUTING.md
Project-URL: Homepage, https://gitlab.com/nummertopia/dexa
Project-URL: Repository, https://gitlab.com/nummertopia/dexa
Project-URL: Work Item Tracker, https://gitlab.com/nummertopia/dexa/-/issues
